Metadata-Version: 2.1
Name: autonlpinsights
Version: 0.0.1
Summary: Auto NLP Insights from text data
Home-page: https://github.com/ncganesh/autonlpinsights
Author: Ganesh N
Author-email: ganeshn.4488@gmail.com
License: UNKNOWN
Platform: UNKNOWN
Classifier: Programming Language :: Python :: 3
Classifier: License :: OSI Approved :: MIT License
Classifier: Operating System :: OS Independent
Requires-Python: >=3.6
